finance/__init__.py
finance/__main__.py
finance_calc-0.5.0.dist-info/METADATA
finance_calc-0.5.0.dist-info/WHEEL
finance_calc-0.5.0.dist-info/top_level.txt
finance_calc-0.5.0.dist-info/RECORD
