Metadata-Version: 2.1
Name: finance_calc
Version: 0.5.0
Author: Plavist Games
